src/pypher/_init_.py
src/pypher/pypher.py
pypher_deadlysloth-0.0.1.dist-info/METADATA
pypher_deadlysloth-0.0.1.dist-info/WHEEL
pypher_deadlysloth-0.0.1.dist-info/licenses/LICENSE
pypher_deadlysloth-0.0.1.dist-info/RECORD
