Metadata-Version: 2.1
Name: Pypher_DeadlySloth
Version: 0.0.1
Summary: A package for string encryption.
Author: DeadlySloth
License-File: LICENSE
Classifier: License :: OSI Approved :: MIT License
Classifier: Operating System :: OS Independent
Classifier: Programming Language :: Python :: 3
Requires-Python: >=3.5
